inspire/__init__.py
inspire/accession.py
inspire/basic_features.py
inspire/calibration.py
inspire/config.py
inspire/constants.py
inspire/convert.py
inspire/custom_logo.py
inspire/download.py
inspire/execute_msfragger.py
inspire/feature_creation.py
inspire/feature_selection.py
inspire/figures.py
inspire/get_spectral_angle.py
inspire/html_template.py
inspire/logo_plot_utils.py
inspire/mz_match.py
inspire/predict_binding.py
inspire/predict_spectra.py
inspire/prepare.py
inspire/prosit.py
inspire/prosit_delta.py
inspire/report.py
inspire/rescore.py
inspire/retention_time.py
inspire/run.py
inspire/spectral_features.py
inspire/utils.py
inspire/validate.py
inspire/input/__init__.py
inspire/input/mascot.py
inspire/input/maxquant.py
inspire/input/mgf.py
inspire/input/mhcpan.py
inspire/input/msfragger.py
inspire/input/msp.py
inspire/input/mzml.py
inspire/input/peaks.py
inspire/input/search_results.py
inspire/input/ssl.py
inspire/pepseek/__init__.py
inspire/pepseek/extract_candidates.py
inspire/pepseek/host_report_template.py
inspire/pepseek/plot_utils.py
inspire/pepseek/proteome_mapping.py
inspire/pepseek/report_template.py
inspire/plot_spectra/__init__.py
inspire/plot_spectra/plot_isobars.py
inspire/plot_spectra/plot_spec_utils.py
inspire/plot_spectra/plot_spectra.py
inspire/quant/__init__.py
inspire/quant/de_analysis.py
inspire/quant/execute.py
inspire/quant/normalise.py
inspire/quant/report_template.py
inspire/quant/utils.py
inspirems-2.0.dist-info/licenses/LICENSE
inspirems-2.0.dist-info/METADATA
inspirems-2.0.dist-info/WHEEL
inspirems-2.0.dist-info/entry_points.txt
inspirems-2.0.dist-info/top_level.txt
inspirems-2.0.dist-info/RECORD
