Metadata-Version: 2.4
Name: inspirems
Version: 2.0
Summary: Helping to integrate Spectral Predictors and Rescoring.
Author: John Cormican, Juliane Liepe, Martin Pasen
Author-email: juliane.liepe@mpinat.mpg.de
Project-URL: Homepage, https://github.com/QuantSysBio/inSPIRE
Project-URL: Tracker, https://github.com/QuantSysBio/inSPIRE/issues
Requires-Python: >=3.11
License-File: LICENSE
Requires-Dist: absl-py==2.0.0
Requires-Dist: astunparse==1.6.3
Requires-Dist: biopython==1.83
Requires-Dist: cachetools==5.3.2
Requires-Dist: certifi==2023.11.17
Requires-Dist: charset-normalizer==3.3.2
Requires-Dist: contourpy==1.2.0
Requires-Dist: cycler==0.12.1
Requires-Dist: docker==7.0.0
Requires-Dist: flatbuffers==23.5.26
Requires-Dist: fonttools==4.45.1
Requires-Dist: gast==0.5.4
Requires-Dist: google-auth==2.23.4
Requires-Dist: google-auth-oauthlib==1.1.0
Requires-Dist: google-pasta==0.2.0
Requires-Dist: grpcio==1.59.3
Requires-Dist: h5py==3.10.0
Requires-Dist: idna==3.4
Requires-Dist: joblib==1.3.2
Requires-Dist: kaleido==0.2.1
Requires-Dist: keras==2.15.0
Requires-Dist: kiwisolver==1.4.5
Requires-Dist: libclang==16.0.6
Requires-Dist: lxml==4.9.3
Requires-Dist: logomaker==0.8
Requires-Dist: Markdown==3.5.1
Requires-Dist: MarkupSafe==2.1.3
Requires-Dist: matplotlib==3.8.2
Requires-Dist: ml-dtypes==0.2.0
Requires-Dist: numpy==1.26.2
Requires-Dist: oauthlib==3.2.2
Requires-Dist: opt-einsum==3.3.0
Requires-Dist: packaging==23.2
Requires-Dist: pandas==2.1.3
Requires-Dist: patsy==0.5.3
Requires-Dist: Pillow==10.1.0
Requires-Dist: plotly==5.18.0
Requires-Dist: polars==0.19.15
Requires-Dist: protobuf==4.23.4
Requires-Dist: pyarrow==14.0.1
Requires-Dist: pyasn1==0.5.1
Requires-Dist: pyasn1-modules==0.3.0
Requires-Dist: pyparsing==3.1.1
Requires-Dist: PyPDF2==3.0.1
Requires-Dist: pyteomics==4.6.3
Requires-Dist: python-dateutil==2.8.2
Requires-Dist: PyYAML==6.0.1
Requires-Dist: requests==2.31.0
Requires-Dist: requests-oauthlib==1.3.1
Requires-Dist: rsa==4.9
Requires-Dist: scikit-learn==1.3.2
Requires-Dist: scipy==1.11.4
Requires-Dist: seaborn==0.13.0
Requires-Dist: six==1.16.0
Requires-Dist: statsmodels==0.14.0
Requires-Dist: tenacity==8.2.3
Requires-Dist: tensorboard==2.15.1
Requires-Dist: tensorboard-data-server==0.7.2
Requires-Dist: tensorflow==2.15.0
Requires-Dist: tensorflow-estimator==2.15.0
Requires-Dist: termcolor==2.3.0
Requires-Dist: threadpoolctl==3.2.0
Requires-Dist: typing_extensions==4.8.0
Requires-Dist: tzdata==2023.3
Requires-Dist: urllib3==2.1.0
Requires-Dist: Werkzeug==3.0.1
Requires-Dist: wrapt==1.14.1
Requires-Dist: xgboost==2.0.2
Requires-Dist: xlsxwriter==3.1.9
Dynamic: author
Dynamic: author-email
Dynamic: description
Dynamic: description-content-type
Dynamic: license-file
Dynamic: project-url
Dynamic: requires-dist
Dynamic: requires-python
Dynamic: summary
